{
  "decisions": [
    {
      "ticker": "NVDA",
      "status": "done",
      "updated_at": "2026-06-05T14:00:00+08:00",
      "verdict": "BUY",
      "conviction": "High"
    },
    {
      "ticker": "LTRX",
      "status": "done",
      "updated_at": "2026-06-05T14:00:00+08:00",
      "verdict": "WATCH",
      "conviction": "Low"
    },
    {
      "ticker": "MRVL",
      "status": "pending",
      "updated_at": "2026-06-05T10:00:00+08:00"
    },
    {
      "ticker": "AVGO",
      "status": "skip",
      "updated_at": "2026-06-05T10:00:00+08:00"
    },
    {
      "ticker": "GOOGL",
      "status": "pending",
      "updated_at": "2026-06-05T10:00:00+08:00"
    },
    {
      "ticker": "AAPL",
      "status": "done",
      "updated_at": "2026-06-05T10:00:00+08:00"
    },
    {
      "ticker": "META",
      "status": "pending",
      "updated_at": "2026-06-05T10:00:00+08:00"
    },
    {
      "ticker": "COIN",
      "status": "skip",
      "updated_at": "2026-06-05T10:00:00+08:00"
    },
    {
      "ticker": "XLU",
      "status": "pending",
      "updated_at": "2026-06-05T10:00:00+08:00"
    }
  ],
  "last_updated": "2026-06-05T14:00:00+08:00"
}
